{"AllowGuest":true,"ContentType":"JSON","Description":"用户微信登录","Enabled":true,"GetExample":"","ID":"6351c29bfd684697a48343ab9560463d","Imped":false,"NeedAuth":true,"Note":"","OwnerCategory":"用户","PostExample":"{\u000d\u000a\u0009\"token\": \"968f3adb3c36469fb928783a0130b26c\",\u000d\u000a\u0009\"openid\": \"968f3adb3c36469fb928783a0130b26c\",\u000d\u000a\u0009\"mac\": \"968f3adb3c36469fb928783a0130b26c\"\u000d\u000a}","RequestParameters":[{"Description":"微信token","Name":"token","Required":true,"Type":"string"},{"Description":"微信用户openid","Name":"openid","Required":true,"Type":"string"},{"Description":"当前用户机子标识","Name":"mac","Required":true,"Type":"string"}],"Response":"{\u000d\u000a\u0009\"result\": {\u000d\u000a\u0009\u0009\"nick\": \"往事笑忘\",\u000d\u000a\u0009\u0009\"uid\": 20001,\u000d\u000a\u0009\u0009\"sessionid\": \"f22a42de638b43099ec7609a88dfcc42\",\u000d\u000a\u0009\u0009\"faceurl\": \"http:\/\/thirdwx.qlogo.cn\/mmopen\/vi_32\/Q0j4TwGTfTKTpJSoy9WEgJDfiaBxq0ia0SRiatKL37JH5FWdsgJIDR9Zp05hgR5uFeExRw184jicbxrUajibqqsQeaQ\/132\",\u000d\u000a\u0009\u0009\"balance\": \"0.00\"\u000d\u000a\u0009},\u000d\u000a\u0009\"errordes\": \"登陆成功\",\u000d\u000a\u0009\"resultcode\": 200,\u000d\u000a\u0009\"state\": 1\u000d\u000a}","ResponseParameters":[{"Description":"用户昵称","Name":"nick","Type":"string"},{"Description":"用户uid","Name":"uid","Type":"long"},{"Description":"用户skey","Name":"sessionid","Type":"string"},{"Description":"头像","Name":"faceurl","Type":"string"},{"Description":"用户金额","Name":"balance","Type":"decimal"}],"Title":"用户微信登录","Type":"POST","Url":"\/account\/wxapplogin"}